detectem/__init__.py
detectem/cli.py
detectem/core.py
detectem/exceptions.py
detectem/matchers.py
detectem/plugin.py
detectem/response.py
detectem/results.py
detectem/script.lua
detectem/settings.py
detectem/utils.py
detectem/ws.py
detectem/data/wordpress.jl
detectem/plugins/__init__.py
detectem/plugins/angular.py
detectem/plugins/angularjs.py
detectem/plugins/apache.py
detectem/plugins/backbonejs.py
detectem/plugins/crayon-syntax-highlighter.py
detectem/plugins/d3js.py
detectem/plugins/emberjs.py
detectem/plugins/ghost.py
detectem/plugins/helpers.py
detectem/plugins/iis.py
detectem/plugins/joomla.py
detectem/plugins/jquery.py
detectem/plugins/jqueryui.py
detectem/plugins/knockoutjs.py
detectem/plugins/lightbox.py
detectem/plugins/modernizr.py
detectem/plugins/momentjs.py
detectem/plugins/mootools.py
detectem/plugins/nginx.py
detectem/plugins/php.py
detectem/plugins/phusion-passenger.py
detectem/plugins/piwik.py
detectem/plugins/react.py
detectem/plugins/requirejs.py
detectem/plugins/ssl.py
detectem/plugins/underscorejs.py
detectem/plugins/vue.py
detectem/plugins/w3-total-cache.py
detectem/plugins/webpack.py
detectem/plugins/wordpress.py
detectem/plugins/wp-super-cache.py
detectem/plugins/generic/__init__.py
detectem/plugins/generic/wordpress.py
detectem-0.7.3.dist-info/AUTHORS.rst
detectem-0.7.3.dist-info/LICENSE
detectem-0.7.3.dist-info/METADATA
detectem-0.7.3.dist-info/WHEEL
detectem-0.7.3.dist-info/entry_points.txt
detectem-0.7.3.dist-info/top_level.txt
detectem-0.7.3.dist-info/RECORD
